<?xml version="1.0" encoding="UTF-8"?><record_update table="sn_niem_eye_color">
    <sn_niem_eye_color action="INSERT_OR_UPDATE">
        <active>true</active>
        <eye_color>Gray</eye_color>
        <eye_color_code>gry</eye_color_code>
        <sys_class_name>sn_niem_eye_color</sys_class_name>
        <sys_created_by>steven.ly</sys_created_by>
        <sys_created_on>2022-09-01 13:55:08</sys_created_on>
        <sys_id>0e7d9e6f4725d91024e32782846d43a4</sys_id>
        <sys_mod_count>0</sys_mod_count>
        <sys_name/>
        <sys_package display_value="NIEM" source="sn_niem">1e4f5cdbb8320110fa9b96d4e616a3c5</sys_package>
        <sys_policy/>
        <sys_scope display_value="NIEM">1e4f5cdbb8320110fa9b96d4e616a3c5</sys_scope>
        <sys_update_name>sn_niem_eye_color_0e7d9e6f4725d91024e32782846d43a4</sys_update_name>
        <sys_updated_by>steven.ly</sys_updated_by>
        <sys_updated_on>2022-09-01 13:55:08</sys_updated_on>
    </sn_niem_eye_color>
</record_update>
